tiny_scientist/__init__.py
tiny_scientist/budget_checker.py
tiny_scientist/coder.py
tiny_scientist/configs.py
tiny_scientist/data.py
tiny_scientist/fewshot_sample/automated_relational.txt
tiny_scientist/fewshot_sample/framework.pdf
tiny_scientist/fewshot_sample/result.pdf
tiny_scientist/prompts/coder_prompt.yaml
tiny_scientist/prompts/diagram_prompt.yaml
tiny_scientist/prompts/drawer_prompt.yaml
tiny_scientist/prompts/latex_fix_prompt.yaml
tiny_scientist/prompts/reviewer_prompt.yaml
tiny_scientist/prompts/safety_prompt.yaml
tiny_scientist/prompts/thinker_prompt.yaml
tiny_scientist/prompts/writer_prompt.yaml
tiny_scientist/reviewer.py
tiny_scientist/safety_checker.py
tiny_scientist/scientist.py
tiny_scientist/thinker.py
tiny_scientist/tool.py
tiny_scientist/utils/__init__.py
tiny_scientist/utils/bib_manager.py
tiny_scientist/utils/error_handler.py
tiny_scientist/utils/input_formatter.py
tiny_scientist/utils/llm.py
tiny_scientist/utils/output_formatter.py
tiny_scientist/utils/pricing.py
tiny_scientist/utils/water_marker.py
tiny_scientist/writer.py
tiny_scientist-0.1.3.dist-info/LICENSE
tiny_scientist-0.1.3.dist-info/METADATA
tiny_scientist-0.1.3.dist-info/WHEEL
tiny_scientist-0.1.3.dist-info/RECORD
