Metadata-Version: 2.3
Name: tiny-scientist
Version: 0.1.3
Summary: A lightweight framework for building research agents
License: Apache 2.0 License
Author: Haofei Yu
Author-email: yuhaofei44@gmail.com
Requires-Python: >=3.9,<3.12
Classifier: License :: Other/Proprietary License
Classifier: Programming Language :: Python :: 3
Classifier: Programming Language :: Python :: 3.9
Classifier: Programming Language :: Python :: 3.10
Classifier: Programming Language :: Python :: 3.11
Requires-Dist: aider-chat
Requires-Dist: anthropic
Requires-Dist: backoff
Requires-Dist: beartype
Requires-Dist: cairosvg (>=2.7.1,<3.0.0)
Requires-Dist: docker (>=7.1.0,<8.0.0)
Requires-Dist: flask (>=3.0.0,<4.0.0)
Requires-Dist: flask-cors (>=4,<7)
Requires-Dist: flask-socketio (>=5.5.1,<6.0.0)
Requires-Dist: google-generativeai
Requires-Dist: litellm
Requires-Dist: mypy (>=1.8.0,<2.0.0)
Requires-Dist: openai
Requires-Dist: pyalex
Requires-Dist: pydantic (>=2.8.2,<3.0.0)
Requires-Dist: pymupdf (>=1.22.3,<2.0.0)
Requires-Dist: pymupdf4llm
Requires-Dist: pypdf (>=5.3.1,<6.0.0)
Requires-Dist: pyyaml (>=6.0,<7.0)
Requires-Dist: reportlab
Requires-Dist: requests (>=2.28.0,<3.0.0)
Requires-Dist: rich
Requires-Dist: spacy (>=3.0.0,<4.0.0)
Requires-Dist: together
Requires-Dist: toml
